{
    "parent": "minecraft:block/cube",
    "textures": {
        "particle": "barteringstation:block/bartering_station_front",
        "down": "minecraft:block/crimson_planks",
        "up": "barteringstation:block/bartering_station_top",
        "north": "barteringstation:block/bartering_station_front",
        "east": "barteringstation:block/bartering_station_side",
        "south": "barteringstation:block/bartering_station_side",
        "west": "barteringstation:block/bartering_station_front"
    }
}
